{
    "names": [
        {
            "name": "なまけ",
            "language": {
                "name": "jaHrkt"
            }
        },
        {
            "name": "게으름",
            "language": {
                "name": "ko"
            }
        },
        {
            "name": "懶惰",
            "language": {
                "name": "zhHant"
            }
        },
        {
            "name": "Absentéisme",
            "language": {
                "name": "fr"
            }
        },
        {
            "name": "Schnarchnase",
            "language": {
                "name": "de"
            }
        },
        {
            "name": "Ausente",
            "language": {
                "name": "es"
            }
        },
        {
            "name": "Pigrone",
            "language": {
                "name": "it"
            }
        },
        {
            "name": "Truant",
            "language": {
                "name": "en"
            }
        },
        {
            "name": "なまけ",
            "language": {
                "name": "ja"
            }
        },
        {
            "name": "懒惰",
            "language": {
                "name": "zhHans"
            }
        }
    ],
    "front_sprite_url": ""
}